nowcastnet/__init__.py
nowcastnet/evaluate.py
nowcastnet/inference.py
nowcastnet/datasets/__init__.py
nowcastnet/datasets/factory.py
nowcastnet/datasets/radar_dataset.py
nowcastnet/evaluation/__init__.py
nowcastnet/evaluation/metrics.py
nowcastnet/model/__init__.py
nowcastnet/model/nowcastnet.py
nowcastnet/model/modules/__init__.py
nowcastnet/model/modules/shared_modules.py
nowcastnet/model/modules/evolution/__init__.py
nowcastnet/model/modules/evolution/evolution_network.py
nowcastnet/model/modules/evolution/evolution_operator.py
nowcastnet/model/modules/generation/__init__.py
nowcastnet/model/modules/generation/generative_decoder.py
nowcastnet/model/modules/generation/generative_encoder.py
nowcastnet/model/modules/generation/noise_projector.py
nowcastnet/utils/__init__.py
nowcastnet/utils/logging.py
nowcastnet/utils/parsing.py
nowcastnet/utils/preprocessing.py
nowcastnet/utils/visualizing.py
nowcastnet_rewritten-0.1.1.dist-info/licenses/LICENSE
nowcastnet_rewritten-0.1.1.dist-info/METADATA
nowcastnet_rewritten-0.1.1.dist-info/WHEEL
nowcastnet_rewritten-0.1.1.dist-info/top_level.txt
nowcastnet_rewritten-0.1.1.dist-info/RECORD
