Metadata-Version: 2.4
Name: nowcastnet-rewritten
Version: 0.1.1
Summary: A personal reimplementation of NowcastNet inference framework
Author-email: Xinjie Chen <1377232072@qq.com>
License-Expression: MIT
Requires-Python: <3.11,>=3.10
License-File: LICENSE
Requires-Dist: matplotlib>=3.10.1
Requires-Dist: numpy>=2.2.2
Requires-Dist: opencv-python>=4.11.0.86
Requires-Dist: scikit-learn>=1.6.1
Requires-Dist: torch>=2.6.0
Requires-Dist: tomlkit>=0.13.2
Requires-Dist: pysteps<=1.18.0,>=1.14.0
Provides-Extra: full
Requires-Dist: onnx>=1.18.0; extra == "full"
Requires-Dist: onnxruntime>=1.22.0; extra == "full"
Dynamic: license-file
